mp_sdk/__init__.py
mp_sdk/core/__init__.py
mp_sdk/core/credential_manager.py
mp_sdk/core/credential_pool.py
mp_sdk/core/credential_provider.py
mp_sdk/core/push_bullet_client.py
mp_sdk/decorators/__init__.py
mp_sdk/decorators/bank_automation.py
mp_sdk/exceptions/__init__.py
mp_sdk/exceptions/automation_exception.py
mp_sdk/interfaces/__init__.py
mp_sdk/interfaces/pay_function.py
mp_sdk/interfaces/pay_function_factory.py
mp_sdk/interfaces/pay_function_metadata.py
mp_sdk/interfaces/server_interfaces.py
mp_sdk/models/__init__.py
mp_sdk/models/action_result.py
mp_sdk/models/credential_data.py
mp_sdk/models/enums.py
mp_sdk/models/limited_size_cache.py
mp_sdk/models/monitor_account.py
mp_sdk/models/node.py
mp_sdk/models/parsed_transaction.py
mp_sdk/models/pay_context.py
mp_sdk/models/pay_timer_keys.py
mp_sdk/models/payout_batch.py
mp_sdk/models/query_result.py
mp_sdk/models/register_node_info.py
mp_sdk/models/server_session.py
mp_sdk/models/session_data.py
mp_sdk/models/session_keys.py
mp_sdk/models/stop_watch_container.py
mp_sdk/models/upload_states.py
mp_sdk/providers/__init__.py
mp_sdk/providers/bullet_sms_provider.py
mp_sdk/providers/console_provider.py
mp_sdk/providers/server_session_provider.py
mp_sdk/test/__init__.py
mp_sdk/test/mock_server.py
mp_sdk/test/test_driver.py
mp_sdk_py-0.1.0.dist-info/METADATA
mp_sdk_py-0.1.0.dist-info/WHEEL
mp_sdk_py-0.1.0.dist-info/top_level.txt
mp_sdk_py-0.1.0.dist-info/RECORD
