Metadata-Version: 2.1
Name: mp-sdk-py
Version: 0.1.0
Summary: framework for monitor development
Author: bp developer
Requires-Python: >=3.9
Requires-Dist: pytest-playwright >=0.5.2
Requires-Dist: websockets >=13.1
